gaussdecomp/__init__.py
gaussdecomp/cube.py
gaussdecomp/driver.py
gaussdecomp/fitter.py
gaussdecomp/spectrum.py
gaussdecomp/utils.py
gaussdecomp-1.0.26.data/scripts/gaussdecomp
gaussdecomp-1.0.26.dist-info/LICENSE
gaussdecomp-1.0.26.dist-info/METADATA
gaussdecomp-1.0.26.dist-info/WHEEL
gaussdecomp-1.0.26.dist-info/top_level.txt
gaussdecomp-1.0.26.dist-info/RECORD
