Metadata-Version: 2.1
Name: gaussdecomp
Version: 1.0.26
Summary: Gaussian Decomposition
Home-page: https://github.com/dnidever/gaussdecomp
Author: David Nidever
Author-email: dnidever@montana.edu
License: MIT
Platform: UNKNOWN
Requires-Python: >=3.6
License-File: LICENSE
Requires-Dist: numpy
Requires-Dist: astropy (>=4.0)
Requires-Dist: scipy
Requires-Dist: dlnpyutils (>=1.0.3)
Requires-Dist: dill
Provides-Extra: docs
Requires-Dist: sphinx (==3.0.1) ; extra == 'docs'
Requires-Dist: sphinx-astropy ; extra == 'docs'
Requires-Dist: nbsphinx ; extra == 'docs'
Requires-Dist: nbconvert ; extra == 'docs'
Requires-Dist: nbformat ; extra == 'docs'
Requires-Dist: ipykernel ; extra == 'docs'
Provides-Extra: test
Requires-Dist: pytest ; extra == 'test'
Requires-Dist: pytest-astropy ; extra == 'test'
Requires-Dist: ipython ; extra == 'test'
